{
  "format_version": "1.12.0",
  "minecraft:geometry": [
    {
      "description": {
        "identifier": "geometry.model.buthol",
        "texture_width": 128,
        "texture_height": 128,
        "visible_bounds_width": 3,
        "visible_bounds_height": 4,
        "visible_bounds_offset": [
          0,
          1.2,
          0
        ]
      },
      "bones": [
        {
          "name": "root",
          "pivot": [
            0.0,
            24.0,
            0.0
          ],
          "rotation": [
            0.0,
            -180.0,
            0.0
          ]
        },
        {
          "name": "mainbody",
          "pivot": [
            0.0,
            27.3,
            0.0
          ],
          "parent": "root",
          "cubes": [
            {
              "origin": [
                -4.0,
                23.3,
                -4.0
              ],
              "size": [
                8.0,
                4.0,
                8.0
              ],
              "uv": {
                "north": {
                  "uv": [
                    24.0,
                    8.0
                  ],
                  "uv_size": [
                    8.0,
                    4.0
                  ]
                },
                "east": {
                  "uv": [
                    16.0,
                    8.0
                  ],
                  "uv_size": [
                    8.0,
                    4.0
                  ]
                },
                "south": {
                  "uv": [
                    8.0,
                    8.0
                  ],
                  "uv_size": [
                    8.0,
                    4.0
                  ]
                },
                "west": {
                  "uv": [
                    0.0,
                    8.0
                  ],
                  "uv_size": [
                    8.0,
                    4.0
                  ]
                },
                "up": {
                  "uv": [
                    16.0,
                    8.0
                  ],
                  "uv_size": [
                    -8.0,
                    -8.0
                  ]
                },
                "down": {
                  "uv": [
                    24.0,
                    8.0
                  ],
                  "uv_size": [
                    -8.0,
                    -8.0
                  ]
                }
              }
            }
          ]
        },
        {
          "name": "tree3",
          "pivot": [
            -1.8,
            24.6,
            -2.7
          ],
          "parent": "mainbody",
          "rotation": [
            -41.74,
            0.0,
            0.0
          ],
          "cubes": [
            {
              "origin": [
                -2.8,
                20.6,
                -3.7
              ],
              "size": [
                2.0,
                4.0,
                2.0
              ],
              "uv": {
                "north": {
                  "uv": [
                    6.0,
                    2.0
                  ],
                  "uv_size": [
                    2.0,
                    4.0
                  ]
                },
                "east": {
                  "uv": [
                    4.0,
                    2.0
                  ],
                  "uv_size": [
                    2.0,
                    4.0
                  ]
                },
                "south": {
                  "uv": [
                    2.0,
                    2.0
                  ],
                  "uv_size": [
                    2.0,
                    4.0
                  ]
                },
                "west": {
                  "uv": [
                    0.0,
                    2.0
                  ],
                  "uv_size": [
                    2.0,
                    4.0
                  ]
                },
                "up": {
                  "uv": [
                    4.0,
                    2.0
                  ],
                  "uv_size": [
                    -2.0,
                    -2.0
                  ]
                },
                "down": {
                  "uv": [
                    6.0,
                    2.0
                  ],
                  "uv_size": [
                    -2.0,
                    -2.0
                  ]
                }
              }
            }
          ]
        },
        {
          "name": "tree2",
          "pivot": [
            2.7,
            24.6,
            1.4
          ],
          "parent": "mainbody",
          "rotation": [
            138.25986,
            -73.03997,
            -179.99988
          ],
          "cubes": [
            {
              "origin": [
                1.7,
                20.6,
                0.4
              ],
              "size": [
                2.0,
                4.0,
                2.0
              ],
              "uv": {
                "north": {
                  "uv": [
                    30.0,
                    2.0
                  ],
                  "uv_size": [
                    2.0,
                    4.0
                  ]
                },
                "east": {
                  "uv": [
                    28.0,
                    2.0
                  ],
                  "uv_size": [
                    2.0,
                    4.0
                  ]
                },
                "south": {
                  "uv": [
                    26.0,
                    2.0
                  ],
                  "uv_size": [
                    2.0,
                    4.0
                  ]
                },
                "west": {
                  "uv": [
                    24.0,
                    2.0
                  ],
                  "uv_size": [
                    2.0,
                    4.0
                  ]
                },
                "up": {
                  "uv": [
                    28.0,
                    2.0
                  ],
                  "uv_size": [
                    -2.0,
                    -2.0
                  ]
                },
                "down": {
                  "uv": [
                    30.0,
                    2.0
                  ],
                  "uv_size": [
                    -2.0,
                    -2.0
                  ]
                }
              }
            }
          ]
        },
        {
          "name": "tree1",
          "pivot": [
            -3.2,
            24.6,
            2.5
          ],
          "parent": "mainbody",
          "rotation": [
            138.2601,
            57.39001,
            -179.99991
          ],
          "cubes": [
            {
              "origin": [
                -4.2,
                20.6,
                1.5
              ],
              "size": [
                2.0,
                5.0,
                2.0
              ],
              "uv": {
                "north": {
                  "uv": [
                    38.0,
                    2.0
                  ],
                  "uv_size": [
                    2.0,
                    5.0
                  ]
                },
                "east": {
                  "uv": [
                    36.0,
                    2.0
                  ],
                  "uv_size": [
                    2.0,
                    5.0
                  ]
                },
                "south": {
                  "uv": [
                    34.0,
                    2.0
                  ],
                  "uv_size": [
                    2.0,
                    5.0
                  ]
                },
                "west": {
                  "uv": [
                    32.0,
                    2.0
                  ],
                  "uv_size": [
                    2.0,
                    5.0
                  ]
                },
                "up": {
                  "uv": [
                    36.0,
                    2.0
                  ],
                  "uv_size": [
                    -2.0,
                    -2.0
                  ]
                },
                "down": {
                  "uv": [
                    38.0,
                    2.0
                  ],
                  "uv_size": [
                    -2.0,
                    -2.0
                  ]
                }
              }
            }
          ]
        },
        {
          "name": "top",
          "pivot": [
            0.0,
            33.3,
            0.0
          ],
          "parent": "mainbody",
          "cubes": [
            {
              "origin": [
                -5.0,
                25.3,
                -5.0
              ],
              "size": [
                10.0,
                8.0,
                10.0
              ],
              "uv": {
                "north": {
                  "uv": [
                    62.0,
                    10.0
                  ],
                  "uv_size": [
                    10.0,
                    8.0
                  ]
                },
                "east": {
                  "uv": [
                    52.0,
                    10.0
                  ],
                  "uv_size": [
                    10.0,
                    8.0
                  ]
                },
                "south": {
                  "uv": [
                    42.0,
                    10.0
                  ],
                  "uv_size": [
                    10.0,
                    8.0
                  ]
                },
                "west": {
                  "uv": [
                    32.0,
                    10.0
                  ],
                  "uv_size": [
                    10.0,
                    8.0
                  ]
                },
                "up": {
                  "uv": [
                    52.0,
                    10.0
                  ],
                  "uv_size": [
                    -10.0,
                    -10.0
                  ]
                },
                "down": {
                  "uv": [
                    62.0,
                    10.0
                  ],
                  "uv_size": [
                    -10.0,
                    -10.0
                  ]
                }
              }
            }
          ]
        },
        {
          "name": "tree3_1",
          "pivot": [
            -1.8,
            21.6,
            -2.7
          ],
          "parent": "tree3",
          "rotation": [
            10.43,
            0.0,
            0.0
          ],
          "cubes": [
            {
              "origin": [
                -3.3,
                17.6,
                -4.2
              ],
              "size": [
                3.0,
                4.0,
                3.0
              ],
              "uv": {
                "north": {
                  "uv": [
                    71.0,
                    3.0
                  ],
                  "uv_size": [
                    3.0,
                    4.0
                  ]
                },
                "east": {
                  "uv": [
                    68.0,
                    3.0
                  ],
                  "uv_size": [
                    3.0,
                    4.0
                  ]
                },
                "south": {
                  "uv": [
                    65.0,
                    3.0
                  ],
                  "uv_size": [
                    3.0,
                    4.0
                  ]
                },
                "west": {
                  "uv": [
                    62.0,
                    3.0
                  ],
                  "uv_size": [
                    3.0,
                    4.0
                  ]
                },
                "up": {
                  "uv": [
                    68.0,
                    3.0
                  ],
                  "uv_size": [
                    -3.0,
                    -3.0
                  ]
                },
                "down": {
                  "uv": [
                    71.0,
                    3.0
                  ],
                  "uv_size": [
                    -3.0,
                    -3.0
                  ]
                }
              }
            }
          ]
        },
        {
          "name": "tree3_2",
          "pivot": [
            -1.8,
            18.6,
            -2.7
          ],
          "parent": "tree3_1",
          "rotation": [
            15.65,
            0.0,
            0.0
          ],
          "cubes": [
            {
              "origin": [
                -3.8,
                14.6,
                -4.7
              ],
              "size": [
                4.0,
                4.0,
                4.0
              ],
              "uv": {
                "north": {
                  "uv": [
                    86.0,
                    4.0
                  ],
                  "uv_size": [
                    4.0,
                    4.0
                  ]
                },
                "east": {
                  "uv": [
                    82.0,
                    4.0
                  ],
                  "uv_size": [
                    4.0,
                    4.0
                  ]
                },
                "south": {
                  "uv": [
                    78.0,
                    4.0
                  ],
                  "uv_size": [
                    4.0,
                    4.0
                  ]
                },
                "west": {
                  "uv": [
                    74.0,
                    4.0
                  ],
                  "uv_size": [
                    4.0,
                    4.0
                  ]
                },
                "up": {
                  "uv": [
                    82.0,
                    4.0
                  ],
                  "uv_size": [
                    -4.0,
                    -4.0
                  ]
                },
                "down": {
                  "uv": [
                    86.0,
                    4.0
                  ],
                  "uv_size": [
                    -4.0,
                    -4.0
                  ]
                }
              }
            }
          ]
        },
        {
          "name": "poptree3",
          "pivot": [
            -1.8,
            16.2,
            -2.7
          ],
          "parent": "tree3_2",
          "rotation": [
            172.16998,
            13.03999,
            179.99998
          ],
          "cubes": [
            {
              "origin": [
                -4.8,
                -1.8,
                -6.2
              ],
              "size": [
                6.0,
                18.0,
                7.0
              ],
              "uv": {
                "north": {
                  "uv": [
                    110.0,
                    7.0
                  ],
                  "uv_size": [
                    6.0,
                    18.0
                  ]
                },
                "east": {
                  "uv": [
                    103.0,
                    7.0
                  ],
                  "uv_size": [
                    7.0,
                    18.0
                  ]
                },
                "south": {
                  "uv": [
                    97.0,
                    7.0
                  ],
                  "uv_size": [
                    6.0,
                    18.0
                  ]
                },
                "west": {
                  "uv": [
                    90.0,
                    7.0
                  ],
                  "uv_size": [
                    7.0,
                    18.0
                  ]
                },
                "up": {
                  "uv": [
                    103.0,
                    7.0
                  ],
                  "uv_size": [
                    -6.0,
                    -7.0
                  ]
                },
                "down": {
                  "uv": [
                    109.0,
                    7.0
                  ],
                  "uv_size": [
                    -6.0,
                    -7.0
                  ]
                }
              }
            }
          ]
        },
        {
          "name": "body3",
          "pivot": [
            -1.8,
            14.3,
            -2.7
          ],
          "parent": "poptree3",
          "cubes": [
            {
              "origin": [
                -6.3,
                0.3,
                -7.7
              ],
              "size": [
                9.0,
                14.0,
                10.0
              ],
              "uv": {
                "north": {
                  "uv": [
                    29.0,
                    22.0
                  ],
                  "uv_size": [
                    9.0,
                    14.0
                  ]
                },
                "east": {
                  "uv": [
                    19.0,
                    22.0
                  ],
                  "uv_size": [
                    10.0,
                    14.0
                  ]
                },
                "south": {
                  "uv": [
                    10.0,
                    22.0
                  ],
                  "uv_size": [
                    9.0,
                    14.0
                  ]
                },
                "west": {
                  "uv": [
                    0.0,
                    22.0
                  ],
                  "uv_size": [
                    10.0,
                    14.0
                  ]
                },
                "up": {
                  "uv": [
                    19.0,
                    22.0
                  ],
                  "uv_size": [
                    -9.0,
                    -10.0
                  ]
                },
                "down": {
                  "uv": [
                    28.0,
                    22.0
                  ],
                  "uv_size": [
                    -9.0,
                    -10.0
                  ]
                }
              }
            }
          ]
        },
        {
          "name": "pop3",
          "pivot": [
            -1.0,
            2.9,
            -6.8
          ],
          "parent": "body3",
          "rotation": [
            -180.0,
            0.0,
            -23.48
          ],
          "cubes": [
            {
              "origin": [
                -3.5,
                0.4,
                -6.3
              ],
              "size": [
                5.0,
                5.0,
                2.0
              ],
              "uv": {
                "north": {
                  "uv": [
                    118.0,
                    2.0
                  ],
                  "uv_size": [
                    5.0,
                    5.0
                  ]
                },
                "east": {
                  "uv": [
                    116.0,
                    2.0
                  ],
                  "uv_size": [
                    2.0,
                    5.0
                  ]
                },
                "south": {
                  "uv": [
                    111.0,
                    2.0
                  ],
                  "uv_size": [
                    5.0,
                    5.0
                  ]
                },
                "west": {
                  "uv": [
                    109.0,
                    2.0
                  ],
                  "uv_size": [
                    2.0,
                    5.0
                  ]
                },
                "up": {
                  "uv": [
                    116.0,
                    2.0
                  ],
                  "uv_size": [
                    -5.0,
                    -2.0
                  ]
                },
                "down": {
                  "uv": [
                    121.0,
                    2.0
                  ],
                  "uv_size": [
                    -5.0,
                    -2.0
                  ]
                }
              }
            }
          ]
        },
        {
          "name": "pop3_1",
          "pivot": [
            1.1,
            8.0,
            -3.0
          ],
          "parent": "body3",
          "rotation": [
            0.0,
            90.0,
            0.0
          ],
          "cubes": [
            {
              "origin": [
                0.6,
                5.5,
                -2.8
              ],
              "size": [
                3.0,
                5.0,
                2.0
              ],
              "uv": {
                "north": {
                  "uv": [
                    123.0,
                    9.0
                  ],
                  "uv_size": [
                    3.0,
                    5.0
                  ]
                },
                "east": {
                  "uv": [
                    121.0,
                    9.0
                  ],
                  "uv_size": [
                    2.0,
                    5.0
                  ]
                },
                "south": {
                  "uv": [
                    118.0,
                    9.0
                  ],
                  "uv_size": [
                    3.0,
                    5.0
                  ]
                },
                "west": {
                  "uv": [
                    116.0,
                    9.0
                  ],
                  "uv_size": [
                    2.0,
                    5.0
                  ]
                },
                "up": {
                  "uv": [
                    121.0,
                    9.0
                  ],
                  "uv_size": [
                    -3.0,
                    -2.0
                  ]
                },
                "down": {
                  "uv": [
                    124.0,
                    9.0
                  ],
                  "uv_size": [
                    -3.0,
                    -2.0
                  ]
                }
              }
            }
          ]
        },
        {
          "name": "pop3_2",
          "pivot": [
            -1.7,
            8.5,
            1.8
          ],
          "parent": "body3",
          "rotation": [
            0.0,
            0.0,
            41.74
          ],
          "cubes": [
            {
              "origin": [
                -2.2,
                8.0,
                2.0
              ],
              "size": [
                3.0,
                3.0,
                2.0
              ],
              "uv": {
                "north": {
                  "uv": [
                    79.0,
                    10.0
                  ],
                  "uv_size": [
                    3.0,
                    3.0
                  ]
                },
                "east": {
                  "uv": [
                    77.0,
                    10.0
                  ],
                  "uv_size": [
                    2.0,
                    3.0
                  ]
                },
                "south": {
                  "uv": [
                    74.0,
                    10.0
                  ],
                  "uv_size": [
                    3.0,
                    3.0
                  ]
                },
                "west": {
                  "uv": [
                    72.0,
                    10.0
                  ],
                  "uv_size": [
                    2.0,
                    3.0
                  ]
                },
                "up": {
                  "uv": [
                    77.0,
                    10.0
                  ],
                  "uv_size": [
                    -3.0,
                    -2.0
                  ]
                },
                "down": {
                  "uv": [
                    80.0,
                    10.0
                  ],
                  "uv_size": [
                    -3.0,
                    -2.0
                  ]
                }
              }
            }
          ]
        },
        {
          "name": "pop3_3",
          "pivot": [
            -4.4,
            4.4,
            1.2
          ],
          "parent": "body3",
          "rotation": [
            0.0,
            0.0,
            114.78
          ],
          "cubes": [
            {
              "origin": [
                -4.9,
                3.9,
                1.4
              ],
              "size": [
                3.0,
                3.0,
                2.0
              ],
              "uv": {
                "north": {
                  "uv": [
                    87.0,
                    13.0
                  ],
                  "uv_size": [
                    3.0,
                    3.0
                  ]
                },
                "east": {
                  "uv": [
                    85.0,
                    13.0
                  ],
                  "uv_size": [
                    2.0,
                    3.0
                  ]
                },
                "south": {
                  "uv": [
                    82.0,
                    13.0
                  ],
                  "uv_size": [
                    3.0,
                    3.0
                  ]
                },
                "west": {
                  "uv": [
                    80.0,
                    13.0
                  ],
                  "uv_size": [
                    2.0,
                    3.0
                  ]
                },
                "up": {
                  "uv": [
                    85.0,
                    13.0
                  ],
                  "uv_size": [
                    -3.0,
                    -2.0
                  ]
                },
                "down": {
                  "uv": [
                    88.0,
                    13.0
                  ],
                  "uv_size": [
                    -3.0,
                    -2.0
                  ]
                }
              }
            }
          ]
        },
        {
          "name": "pop4_3",
          "pivot": [
            -7.9,
            4.3,
            -3.2
          ],
          "parent": "body3",
          "rotation": [
            0.0,
            90.0,
            0.0
          ],
          "cubes": [
            {
              "origin": [
                -11.4,
                3.8,
                -3.0
              ],
              "size": [
                6.0,
                3.0,
                2.0
              ],
              "uv": {
                "north": {
                  "uv": [
                    80.0,
                    18.0
                  ],
                  "uv_size": [
                    6.0,
                    3.0
                  ]
                },
                "east": {
                  "uv": [
                    78.0,
                    18.0
                  ],
                  "uv_size": [
                    2.0,
                    3.0
                  ]
                },
                "south": {
                  "uv": [
                    72.0,
                    18.0
                  ],
                  "uv_size": [
                    6.0,
                    3.0
                  ]
                },
                "west": {
                  "uv": [
                    70.0,
                    18.0
                  ],
                  "uv_size": [
                    2.0,
                    3.0
                  ]
                },
                "up": {
                  "uv": [
                    78.0,
                    18.0
                  ],
                  "uv_size": [
                    -6.0,
                    -2.0
                  ]
                },
                "down": {
                  "uv": [
                    84.0,
                    18.0
                  ],
                  "uv_size": [
                    -6.0,
                    -2.0
                  ]
                }
              }
            }
          ]
        },
        {
          "name": "pop31",
          "pivot": [
            -1.0,
            2.9,
            -4.2
          ],
          "parent": "pop3",
          "rotation": [
            0.0,
            0.0,
            62.61
          ],
          "cubes": [
            {
              "origin": [
                -2.5,
                1.4,
                -5.1
              ],
              "size": [
                3.0,
                3.0,
                2.0
              ],
              "uv": {
                "north": {
                  "uv": [
                    7.0,
                    14.0
                  ],
                  "uv_size": [
                    3.0,
                    3.0
                  ]
                },
                "east": {
                  "uv": [
                    5.0,
                    14.0
                  ],
                  "uv_size": [
                    2.0,
                    3.0
                  ]
                },
                "south": {
                  "uv": [
                    2.0,
                    14.0
                  ],
                  "uv_size": [
                    3.0,
                    3.0
                  ]
                },
                "west": {
                  "uv": [
                    0.0,
                    14.0
                  ],
                  "uv_size": [
                    2.0,
                    3.0
                  ]
                },
                "up": {
                  "uv": [
                    5.0,
                    14.0
                  ],
                  "uv_size": [
                    -3.0,
                    -2.0
                  ]
                },
                "down": {
                  "uv": [
                    8.0,
                    14.0
                  ],
                  "uv_size": [
                    -3.0,
                    -2.0
                  ]
                }
              }
            }
          ]
        },
        {
          "name": "tree2_1",
          "pivot": [
            2.7,
            21.6,
            1.4
          ],
          "parent": "tree2",
          "rotation": [
            10.43,
            0.0,
            0.0
          ],
          "cubes": [
            {
              "origin": [
                1.2,
                17.6,
                -0.1
              ],
              "size": [
                3.0,
                4.0,
                3.0
              ],
              "uv": {
                "north": {
                  "uv": [
                    47.0,
                    21.0
                  ],
                  "uv_size": [
                    3.0,
                    4.0
                  ]
                },
                "east": {
                  "uv": [
                    44.0,
                    21.0
                  ],
                  "uv_size": [
                    3.0,
                    4.0
                  ]
                },
                "south": {
                  "uv": [
                    41.0,
                    21.0
                  ],
                  "uv_size": [
                    3.0,
                    4.0
                  ]
                },
                "west": {
                  "uv": [
                    38.0,
                    21.0
                  ],
                  "uv_size": [
                    3.0,
                    4.0
                  ]
                },
                "up": {
                  "uv": [
                    44.0,
                    21.0
                  ],
                  "uv_size": [
                    -3.0,
                    -3.0
                  ]
                },
                "down": {
                  "uv": [
                    47.0,
                    21.0
                  ],
                  "uv_size": [
                    -3.0,
                    -3.0
                  ]
                }
              }
            }
          ]
        },
        {
          "name": "tree2_2",
          "pivot": [
            2.7,
            18.6,
            1.4
          ],
          "parent": "tree2_1",
          "rotation": [
            15.65,
            0.0,
            0.0
          ],
          "cubes": [
            {
              "origin": [
                0.7,
                14.6,
                -0.6
              ],
              "size": [
                4.0,
                4.0,
                4.0
              ],
              "uv": {
                "north": {
                  "uv": [
                    62.0,
                    22.0
                  ],
                  "uv_size": [
                    4.0,
                    4.0
                  ]
                },
                "east": {
                  "uv": [
                    58.0,
                    22.0
                  ],
                  "uv_size": [
                    4.0,
                    4.0
                  ]
                },
                "south": {
                  "uv": [
                    54.0,
                    22.0
                  ],
                  "uv_size": [
                    4.0,
                    4.0
                  ]
                },
                "west": {
                  "uv": [
                    50.0,
                    22.0
                  ],
                  "uv_size": [
                    4.0,
                    4.0
                  ]
                },
                "up": {
                  "uv": [
                    58.0,
                    22.0
                  ],
                  "uv_size": [
                    -4.0,
                    -4.0
                  ]
                },
                "down": {
                  "uv": [
                    62.0,
                    22.0
                  ],
                  "uv_size": [
                    -4.0,
                    -4.0
                  ]
                }
              }
            }
          ]
        },
        {
          "name": "poptree2",
          "pivot": [
            2.7,
            16.2,
            1.4
          ],
          "parent": "tree2_2",
          "rotation": [
            9.9999,
            62.60998,
            -0.0001
          ],
          "cubes": [
            {
              "origin": [
                -0.3,
                -1.8,
                -2.1
              ],
              "size": [
                6.0,
                18.0,
                7.0
              ],
              "uv": {
                "north": {
                  "uv": [
                    79.0,
                    28.0
                  ],
                  "uv_size": [
                    6.0,
                    18.0
                  ]
                },
                "east": {
                  "uv": [
                    72.0,
                    28.0
                  ],
                  "uv_size": [
                    7.0,
                    18.0
                  ]
                },
                "south": {
                  "uv": [
                    66.0,
                    28.0
                  ],
                  "uv_size": [
                    6.0,
                    18.0
                  ]
                },
                "west": {
                  "uv": [
                    59.0,
                    28.0
                  ],
                  "uv_size": [
                    7.0,
                    18.0
                  ]
                },
                "up": {
                  "uv": [
                    72.0,
                    28.0
                  ],
                  "uv_size": [
                    -6.0,
                    -7.0
                  ]
                },
                "down": {
                  "uv": [
                    78.0,
                    28.0
                  ],
                  "uv_size": [
                    -6.0,
                    -7.0
                  ]
                }
              }
            }
          ]
        },
        {
          "name": "body2",
          "pivot": [
            2.7,
            14.3,
            1.4
          ],
          "parent": "poptree2",
          "cubes": [
            {
              "origin": [
                -1.8,
                0.3,
                -3.6
              ],
              "size": [
                9.0,
                14.0,
                10.0
              ],
              "uv": {
                "north": {
                  "uv": [
                    114.0,
                    35.0
                  ],
                  "uv_size": [
                    9.0,
                    14.0
                  ]
                },
                "east": {
                  "uv": [
                    104.0,
                    35.0
                  ],
                  "uv_size": [
                    10.0,
                    14.0
                  ]
                },
                "south": {
                  "uv": [
                    95.0,
                    35.0
                  ],
                  "uv_size": [
                    9.0,
                    14.0
                  ]
                },
                "west": {
                  "uv": [
                    85.0,
                    35.0
                  ],
                  "uv_size": [
                    10.0,
                    14.0
                  ]
                },
                "up": {
                  "uv": [
                    104.0,
                    35.0
                  ],
                  "uv_size": [
                    -9.0,
                    -10.0
                  ]
                },
                "down": {
                  "uv": [
                    113.0,
                    35.0
                  ],
                  "uv_size": [
                    -9.0,
                    -10.0
                  ]
                }
              }
            }
          ]
        },
        {
          "name": "pop2",
          "pivot": [
            3.5,
            5.3,
            -2.7
          ],
          "parent": "body2",
          "rotation": [
            -180.0,
            0.0,
            7.83
          ],
          "cubes": [
            {
              "origin": [
                1.0,
                2.8,
                -2.2
              ],
              "size": [
                5.0,
                5.0,
                2.0
              ],
              "uv": {
                "north": {
                  "uv": [
                    47.0,
                    27.0
                  ],
                  "uv_size": [
                    5.0,
                    5.0
                  ]
                },
                "east": {
                  "uv": [
                    45.0,
                    27.0
                  ],
                  "uv_size": [
                    2.0,
                    5.0
                  ]
                },
                "south": {
                  "uv": [
                    40.0,
                    27.0
                  ],
                  "uv_size": [
                    5.0,
                    5.0
                  ]
                },
                "west": {
                  "uv": [
                    38.0,
                    27.0
                  ],
                  "uv_size": [
                    2.0,
                    5.0
                  ]
                },
                "up": {
                  "uv": [
                    45.0,
                    27.0
                  ],
                  "uv_size": [
                    -5.0,
                    -2.0
                  ]
                },
                "down": {
                  "uv": [
                    50.0,
                    27.0
                  ],
                  "uv_size": [
                    -5.0,
                    -2.0
                  ]
                }
              }
            }
          ]
        },
        {
          "name": "pop2_1",
          "pivot": [
            5.6,
            8.2,
            2.7
          ],
          "parent": "body2",
          "rotation": [
            0.0,
            90.0,
            0.0
          ],
          "cubes": [
            {
              "origin": [
                4.1,
                -0.3,
                2.9
              ],
              "size": [
                4.0,
                11.0,
                2.0
              ],
              "uv": {
                "north": {
                  "uv": [
                    46.0,
                    34.0
                  ],
                  "uv_size": [
                    4.0,
                    11.0
                  ]
                },
                "east": {
                  "uv": [
                    44.0,
                    34.0
                  ],
                  "uv_size": [
                    2.0,
                    11.0
                  ]
                },
                "south": {
                  "uv": [
                    40.0,
                    34.0
                  ],
                  "uv_size": [
                    4.0,
                    11.0
                  ]
                },
                "west": {
                  "uv": [
                    38.0,
                    34.0
                  ],
                  "uv_size": [
                    2.0,
                    11.0
                  ]
                },
                "up": {
                  "uv": [
                    44.0,
                    34.0
                  ],
                  "uv_size": [
                    -4.0,
                    -2.0
                  ]
                },
                "down": {
                  "uv": [
                    48.0,
                    34.0
                  ],
                  "uv_size": [
                    -4.0,
                    -2.0
                  ]
                }
              }
            }
          ]
        },
        {
          "name": "pop2_2",
          "pivot": [
            2.8,
            8.5,
            5.9
          ],
          "parent": "body2",
          "rotation": [
            0.0,
            0.0,
            15.65
          ],
          "cubes": [
            {
              "origin": [
                2.3,
                8.0,
                6.1
              ],
              "size": [
                3.0,
                3.0,
                2.0
              ],
              "uv": {
                "north": {
                  "uv": [
                    123.0,
                    16.0
                  ],
                  "uv_size": [
                    3.0,
                    3.0
                  ]
                },
                "east": {
                  "uv": [
                    121.0,
                    16.0
                  ],
                  "uv_size": [
                    2.0,
                    3.0
                  ]
                },
                "south": {
                  "uv": [
                    118.0,
                    16.0
                  ],
                  "uv_size": [
                    3.0,
                    3.0
                  ]
                },
                "west": {
                  "uv": [
                    116.0,
                    16.0
                  ],
                  "uv_size": [
                    2.0,
                    3.0
                  ]
                },
                "up": {
                  "uv": [
                    121.0,
                    16.0
                  ],
                  "uv_size": [
                    -3.0,
                    -2.0
                  ]
                },
                "down": {
                  "uv": [
                    124.0,
                    16.0
                  ],
                  "uv_size": [
                    -3.0,
                    -2.0
                  ]
                }
              }
            }
          ]
        },
        {
          "name": "pop2_3",
          "pivot": [
            2.2,
            5.7,
            5.1
          ],
          "parent": "body2",
          "rotation": [
            0.0,
            0.0,
            143.48
          ],
          "cubes": [
            {
              "origin": [
                1.7,
                5.2,
                5.3
              ],
              "size": [
                3.0,
                3.0,
                2.0
              ],
              "uv": {
                "north": {
                  "uv": [
                    7.0,
                    19.0
                  ],
                  "uv_size": [
                    3.0,
                    3.0
                  ]
                },
                "east": {
                  "uv": [
                    5.0,
                    19.0
                  ],
                  "uv_size": [
                    2.0,
                    3.0
                  ]
                },
                "south": {
                  "uv": [
                    2.0,
                    19.0
                  ],
                  "uv_size": [
                    3.0,
                    3.0
                  ]
                },
                "west": {
                  "uv": [
                    0.0,
                    19.0
                  ],
                  "uv_size": [
                    2.0,
                    3.0
                  ]
                },
                "up": {
                  "uv": [
                    5.0,
                    19.0
                  ],
                  "uv_size": [
                    -3.0,
                    -2.0
                  ]
                },
                "down": {
                  "uv": [
                    8.0,
                    19.0
                  ],
                  "uv_size": [
                    -3.0,
                    -2.0
                  ]
                }
              }
            }
          ]
        },
        {
          "name": "pop2_4",
          "pivot": [
            -3.4,
            7.5,
            0.9
          ],
          "parent": "body2",
          "rotation": [
            0.0,
            90.0,
            0.0
          ],
          "cubes": [
            {
              "origin": [
                -6.9,
                5.0,
                1.1
              ],
              "size": [
                6.0,
                5.0,
                2.0
              ],
              "uv": {
                "north": {
                  "uv": [
                    10.0,
                    38.0
                  ],
                  "uv_size": [
                    6.0,
                    5.0
                  ]
                },
                "east": {
                  "uv": [
                    8.0,
                    38.0
                  ],
                  "uv_size": [
                    2.0,
                    5.0
                  ]
                },
                "south": {
                  "uv": [
                    2.0,
                    38.0
                  ],
                  "uv_size": [
                    6.0,
                    5.0
                  ]
                },
                "west": {
                  "uv": [
                    0.0,
                    38.0
                  ],
                  "uv_size": [
                    2.0,
                    5.0
                  ]
                },
                "up": {
                  "uv": [
                    8.0,
                    38.0
                  ],
                  "uv_size": [
                    -6.0,
                    -2.0
                  ]
                },
                "down": {
                  "uv": [
                    14.0,
                    38.0
                  ],
                  "uv_size": [
                    -6.0,
                    -2.0
                  ]
                }
              }
            }
          ]
        },
        {
          "name": "pop21",
          "pivot": [
            3.5,
            5.3,
            -0.1
          ],
          "parent": "pop2",
          "rotation": [
            0.0,
            0.0,
            5.22
          ],
          "cubes": [
            {
              "origin": [
                2.0,
                3.8,
                -1.0
              ],
              "size": [
                3.0,
                3.0,
                2.0
              ],
              "uv": {
                "north": {
                  "uv": [
                    123.0,
                    21.0
                  ],
                  "uv_size": [
                    3.0,
                    3.0
                  ]
                },
                "east": {
                  "uv": [
                    121.0,
                    21.0
                  ],
                  "uv_size": [
                    2.0,
                    3.0
                  ]
                },
                "south": {
                  "uv": [
                    118.0,
                    21.0
                  ],
                  "uv_size": [
                    3.0,
                    3.0
                  ]
                },
                "west": {
                  "uv": [
                    116.0,
                    21.0
                  ],
                  "uv_size": [
                    2.0,
                    3.0
                  ]
                },
                "up": {
                  "uv": [
                    121.0,
                    21.0
                  ],
                  "uv_size": [
                    -3.0,
                    -2.0
                  ]
                },
                "down": {
                  "uv": [
                    124.0,
                    21.0
                  ],
                  "uv_size": [
                    -3.0,
                    -2.0
                  ]
                }
              }
            }
          ]
        },
        {
          "name": "tree1_1",
          "pivot": [
            -3.2,
            21.6,
            2.5
          ],
          "parent": "tree1",
          "rotation": [
            10.43,
            0.0,
            0.0
          ],
          "cubes": [
            {
              "origin": [
                -4.7,
                17.6,
                1.0
              ],
              "size": [
                3.0,
                4.0,
                3.0
              ],
              "uv": {
                "north": {
                  "uv": [
                    87.0,
                    24.0
                  ],
                  "uv_size": [
                    3.0,
                    4.0
                  ]
                },
                "east": {
                  "uv": [
                    84.0,
                    24.0
                  ],
                  "uv_size": [
                    3.0,
                    4.0
                  ]
                },
                "south": {
                  "uv": [
                    81.0,
                    24.0
                  ],
                  "uv_size": [
                    3.0,
                    4.0
                  ]
                },
                "west": {
                  "uv": [
                    78.0,
                    24.0
                  ],
                  "uv_size": [
                    3.0,
                    4.0
                  ]
                },
                "up": {
                  "uv": [
                    84.0,
                    24.0
                  ],
                  "uv_size": [
                    -3.0,
                    -3.0
                  ]
                },
                "down": {
                  "uv": [
                    87.0,
                    24.0
                  ],
                  "uv_size": [
                    -3.0,
                    -3.0
                  ]
                }
              }
            }
          ]
        },
        {
          "name": "tree1_2",
          "pivot": [
            -3.2,
            18.6,
            2.5
          ],
          "parent": "tree1_1",
          "rotation": [
            15.65,
            0.0,
            0.0
          ],
          "cubes": [
            {
              "origin": [
                -5.2,
                14.6,
                0.5
              ],
              "size": [
                4.0,
                4.0,
                4.0
              ],
              "uv": {
                "north": {
                  "uv": [
                    28.0,
                    40.0
                  ],
                  "uv_size": [
                    4.0,
                    4.0
                  ]
                },
                "east": {
                  "uv": [
                    24.0,
                    40.0
                  ],
                  "uv_size": [
                    4.0,
                    4.0
                  ]
                },
                "south": {
                  "uv": [
                    20.0,
                    40.0
                  ],
                  "uv_size": [
                    4.0,
                    4.0
                  ]
                },
                "west": {
                  "uv": [
                    16.0,
                    40.0
                  ],
                  "uv_size": [
                    4.0,
                    4.0
                  ]
                },
                "up": {
                  "uv": [
                    24.0,
                    40.0
                  ],
                  "uv_size": [
                    -4.0,
                    -4.0
                  ]
                },
                "down": {
                  "uv": [
                    28.0,
                    40.0
                  ],
                  "uv_size": [
                    -4.0,
                    -4.0
                  ]
                }
              }
            }
          ]
        },
        {
          "name": "poptree1",
          "pivot": [
            -3.2,
            16.2,
            2.5
          ],
          "parent": "tree1_2",
          "rotation": [
            180.0,
            88.7,
            180.0
          ],
          "cubes": [
            {
              "origin": [
                -6.2,
                -1.8,
                -1.0
              ],
              "size": [
                6.0,
                18.0,
                7.0
              ],
              "uv": {
                "north": {
                  "uv": [
                    20.0,
                    51.0
                  ],
                  "uv_size": [
                    6.0,
                    18.0
                  ]
                },
                "east": {
                  "uv": [
                    13.0,
                    51.0
                  ],
                  "uv_size": [
                    7.0,
                    18.0
                  ]
                },
                "south": {
                  "uv": [
                    7.0,
                    51.0
                  ],
                  "uv_size": [
                    6.0,
                    18.0
                  ]
                },
                "west": {
                  "uv": [
                    0.0,
                    51.0
                  ],
                  "uv_size": [
                    7.0,
                    18.0
                  ]
                },
                "up": {
                  "uv": [
                    13.0,
                    51.0
                  ],
                  "uv_size": [
                    -6.0,
                    -7.0
                  ]
                },
                "down": {
                  "uv": [
                    19.0,
                    51.0
                  ],
                  "uv_size": [
                    -6.0,
                    -7.0
                  ]
                }
              }
            }
          ]
        },
        {
          "name": "body1",
          "pivot": [
            -3.2,
            14.3,
            2.5
          ],
          "parent": "poptree1",
          "cubes": [
            {
              "origin": [
                -7.7,
                0.3,
                -2.5
              ],
              "size": [
                9.0,
                14.0,
                10.0
              ],
              "uv": {
                "north": {
                  "uv": [
                    55.0,
                    55.0
                  ],
                  "uv_size": [
                    9.0,
                    14.0
                  ]
                },
                "east": {
                  "uv": [
                    45.0,
                    55.0
                  ],
                  "uv_size": [
                    10.0,
                    14.0
                  ]
                },
                "south": {
                  "uv": [
                    36.0,
                    55.0
                  ],
                  "uv_size": [
                    9.0,
                    14.0
                  ]
                },
                "west": {
                  "uv": [
                    26.0,
                    55.0
                  ],
                  "uv_size": [
                    10.0,
                    14.0
                  ]
                },
                "up": {
                  "uv": [
                    45.0,
                    55.0
                  ],
                  "uv_size": [
                    -9.0,
                    -10.0
                  ]
                },
                "down": {
                  "uv": [
                    54.0,
                    55.0
                  ],
                  "uv_size": [
                    -9.0,
                    -10.0
                  ]
                }
              }
            }
          ]
        },
        {
          "name": "pop1",
          "pivot": [
            -2.4,
            8.1,
            -1.6
          ],
          "parent": "body1",
          "rotation": [
            -180.0,
            0.0,
            49.57
          ],
          "cubes": [
            {
              "origin": [
                -4.9,
                5.6,
                -1.1
              ],
              "size": [
                5.0,
                5.0,
                2.0
              ],
              "uv": {
                "north": {
                  "uv": [
                    122.0,
                    27.0
                  ],
                  "uv_size": [
                    5.0,
                    5.0
                  ]
                },
                "east": {
                  "uv": [
                    120.0,
                    27.0
                  ],
                  "uv_size": [
                    2.0,
                    5.0
                  ]
                },
                "south": {
                  "uv": [
                    115.0,
                    27.0
                  ],
                  "uv_size": [
                    5.0,
                    5.0
                  ]
                },
                "west": {
                  "uv": [
                    113.0,
                    27.0
                  ],
                  "uv_size": [
                    2.0,
                    5.0
                  ]
                },
                "up": {
                  "uv": [
                    120.0,
                    27.0
                  ],
                  "uv_size": [
                    -5.0,
                    -2.0
                  ]
                },
                "down": {
                  "uv": [
                    125.0,
                    27.0
                  ],
                  "uv_size": [
                    -5.0,
                    -2.0
                  ]
                }
              }
            }
          ]
        },
        {
          "name": "pop1_1",
          "pivot": [
            -0.3,
            1.8,
            2.2
          ],
          "parent": "body1",
          "rotation": [
            0.0,
            90.0,
            0.0
          ],
          "cubes": [
            {
              "origin": [
                -2.8,
                -0.7,
                2.4
              ],
              "size": [
                5.0,
                5.0,
                2.0
              ],
              "uv": {
                "north": {
                  "uv": [
                    28.0,
                    46.0
                  ],
                  "uv_size": [
                    5.0,
                    5.0
                  ]
                },
                "east": {
                  "uv": [
                    26.0,
                    46.0
                  ],
                  "uv_size": [
                    2.0,
                    5.0
                  ]
                },
                "south": {
                  "uv": [
                    21.0,
                    46.0
                  ],
                  "uv_size": [
                    5.0,
                    5.0
                  ]
                },
                "west": {
                  "uv": [
                    19.0,
                    46.0
                  ],
                  "uv_size": [
                    2.0,
                    5.0
                  ]
                },
                "up": {
                  "uv": [
                    26.0,
                    46.0
                  ],
                  "uv_size": [
                    -5.0,
                    -2.0
                  ]
                },
                "down": {
                  "uv": [
                    31.0,
                    46.0
                  ],
                  "uv_size": [
                    -5.0,
                    -2.0
                  ]
                }
              }
            }
          ]
        },
        {
          "name": "pop1_2",
          "pivot": [
            -3.1,
            4.8,
            7.0
          ],
          "parent": "body1",
          "rotation": [
            0.0,
            0.0,
            -39.13
          ],
          "cubes": [
            {
              "origin": [
                -3.6,
                4.3,
                7.2
              ],
              "size": [
                3.0,
                3.0,
                2.0
              ],
              "uv": {
                "north": {
                  "uv": [
                    92.0,
                    30.0
                  ],
                  "uv_size": [
                    3.0,
                    3.0
                  ]
                },
                "east": {
                  "uv": [
                    90.0,
                    30.0
                  ],
                  "uv_size": [
                    2.0,
                    3.0
                  ]
                },
                "south": {
                  "uv": [
                    87.0,
                    30.0
                  ],
                  "uv_size": [
                    3.0,
                    3.0
                  ]
                },
                "west": {
                  "uv": [
                    85.0,
                    30.0
                  ],
                  "uv_size": [
                    2.0,
                    3.0
                  ]
                },
                "up": {
                  "uv": [
                    90.0,
                    30.0
                  ],
                  "uv_size": [
                    -3.0,
                    -2.0
                  ]
                },
                "down": {
                  "uv": [
                    93.0,
                    30.0
                  ],
                  "uv_size": [
                    -3.0,
                    -2.0
                  ]
                }
              }
            }
          ]
        },
        {
          "name": "pop1_3",
          "pivot": [
            -5.8,
            2.8,
            6.4
          ],
          "parent": "body1",
          "rotation": [
            0.0,
            0.0,
            88.7
          ],
          "cubes": [
            {
              "origin": [
                -6.3,
                2.3,
                6.6
              ],
              "size": [
                3.0,
                3.0,
                2.0
              ],
              "uv": {
                "north": {
                  "uv": [
                    61.0,
                    48.0
                  ],
                  "uv_size": [
                    3.0,
                    3.0
                  ]
                },
                "east": {
                  "uv": [
                    59.0,
                    48.0
                  ],
                  "uv_size": [
                    2.0,
                    3.0
                  ]
                },
                "south": {
                  "uv": [
                    56.0,
                    48.0
                  ],
                  "uv_size": [
                    3.0,
                    3.0
                  ]
                },
                "west": {
                  "uv": [
                    54.0,
                    48.0
                  ],
                  "uv_size": [
                    2.0,
                    3.0
                  ]
                },
                "up": {
                  "uv": [
                    59.0,
                    48.0
                  ],
                  "uv_size": [
                    -3.0,
                    -2.0
                  ]
                },
                "down": {
                  "uv": [
                    62.0,
                    48.0
                  ],
                  "uv_size": [
                    -3.0,
                    -2.0
                  ]
                }
              }
            }
          ]
        },
        {
          "name": "pop1_4",
          "pivot": [
            -9.3,
            7.5,
            2.0
          ],
          "parent": "body1",
          "rotation": [
            0.0,
            90.0,
            0.0
          ],
          "cubes": [
            {
              "origin": [
                -12.8,
                1.0,
                2.2
              ],
              "size": [
                6.0,
                9.0,
                2.0
              ],
              "uv": {
                "north": {
                  "uv": [
                    74.0,
                    48.0
                  ],
                  "uv_size": [
                    6.0,
                    9.0
                  ]
                },
                "east": {
                  "uv": [
                    72.0,
                    48.0
                  ],
                  "uv_size": [
                    2.0,
                    9.0
                  ]
                },
                "south": {
                  "uv": [
                    66.0,
                    48.0
                  ],
                  "uv_size": [
                    6.0,
                    9.0
                  ]
                },
                "west": {
                  "uv": [
                    64.0,
                    48.0
                  ],
                  "uv_size": [
                    2.0,
                    9.0
                  ]
                },
                "up": {
                  "uv": [
                    72.0,
                    48.0
                  ],
                  "uv_size": [
                    -6.0,
                    -2.0
                  ]
                },
                "down": {
                  "uv": [
                    78.0,
                    48.0
                  ],
                  "uv_size": [
                    -6.0,
                    -2.0
                  ]
                }
              }
            }
          ]
        },
        {
          "name": "pop11",
          "pivot": [
            -2.4,
            8.1,
            1.0
          ],
          "parent": "pop1",
          "rotation": [
            0.0,
            0.0,
            62.61
          ],
          "cubes": [
            {
              "origin": [
                -3.9,
                6.6,
                0.1
              ],
              "size": [
                3.0,
                3.0,
                2.0
              ],
              "uv": {
                "north": {
                  "uv": [
                    87.0,
                    51.0
                  ],
                  "uv_size": [
                    3.0,
                    3.0
                  ]
                },
                "east": {
                  "uv": [
                    85.0,
                    51.0
                  ],
                  "uv_size": [
                    2.0,
                    3.0
                  ]
                },
                "south": {
                  "uv": [
                    82.0,
                    51.0
                  ],
                  "uv_size": [
                    3.0,
                    3.0
                  ]
                },
                "west": {
                  "uv": [
                    80.0,
                    51.0
                  ],
                  "uv_size": [
                    2.0,
                    3.0
                  ]
                },
                "up": {
                  "uv": [
                    85.0,
                    51.0
                  ],
                  "uv_size": [
                    -3.0,
                    -2.0
                  ]
                },
                "down": {
                  "uv": [
                    88.0,
                    51.0
                  ],
                  "uv_size": [
                    -3.0,
                    -2.0
                  ]
                }
              }
            }
          ]
        },
        {
          "name": "top_1",
          "pivot": [
            0.0,
            39.3,
            0.0
          ],
          "parent": "top",
          "cubes": [
            {
              "origin": [
                -1.5,
                32.3,
                -1.5
              ],
              "size": [
                3.0,
                7.0,
                3.0
              ],
              "uv": {
                "north": {
                  "uv": [
                    99.0,
                    52.0
                  ],
                  "uv_size": [
                    3.0,
                    7.0
                  ]
                },
                "east": {
                  "uv": [
                    96.0,
                    52.0
                  ],
                  "uv_size": [
                    3.0,
                    7.0
                  ]
                },
                "south": {
                  "uv": [
                    93.0,
                    52.0
                  ],
                  "uv_size": [
                    3.0,
                    7.0
                  ]
                },
                "west": {
                  "uv": [
                    90.0,
                    52.0
                  ],
                  "uv_size": [
                    3.0,
                    7.0
                  ]
                },
                "up": {
                  "uv": [
                    96.0,
                    52.0
                  ],
                  "uv_size": [
                    -3.0,
                    -3.0
                  ]
                },
                "down": {
                  "uv": [
                    99.0,
                    52.0
                  ],
                  "uv_size": [
                    -3.0,
                    -3.0
                  ]
                }
              }
            }
          ]
        },
        {
          "name": "top_2",
          "pivot": [
            0.0,
            40.8,
            0.0
          ],
          "parent": "top_1",
          "cubes": [
            {
              "origin": [
                -2.0,
                38.8,
                -2.0
              ],
              "size": [
                4.0,
                2.0,
                4.0
              ],
              "uv": {
                "north": {
                  "uv": [
                    114.0,
                    53.0
                  ],
                  "uv_size": [
                    4.0,
                    2.0
                  ]
                },
                "east": {
                  "uv": [
                    110.0,
                    53.0
                  ],
                  "uv_size": [
                    4.0,
                    2.0
                  ]
                },
                "south": {
                  "uv": [
                    106.0,
                    53.0
                  ],
                  "uv_size": [
                    4.0,
                    2.0
                  ]
                },
                "west": {
                  "uv": [
                    102.0,
                    53.0
                  ],
                  "uv_size": [
                    4.0,
                    2.0
                  ]
                },
                "up": {
                  "uv": [
                    110.0,
                    53.0
                  ],
                  "uv_size": [
                    -4.0,
                    -4.0
                  ]
                },
                "down": {
                  "uv": [
                    114.0,
                    53.0
                  ],
                  "uv_size": [
                    -4.0,
                    -4.0
                  ]
                }
              }
            }
          ]
        },
        {
          "name": "wing1",
          "pivot": [
            -1.2,
            36.3,
            -1.1
          ],
          "parent": "top_1",
          "cubes": [
            {
              "origin": [
                -11.2,
                35.3,
                -5.6
              ],
              "size": [
                10.0,
                1.0,
                9.0
              ],
              "uv": {
                "north": {
                  "uv": [
                    92.0,
                    68.0
                  ],
                  "uv_size": [
                    10.0,
                    1.0
                  ]
                },
                "east": {
                  "uv": [
                    83.0,
                    68.0
                  ],
                  "uv_size": [
                    9.0,
                    1.0
                  ]
                },
                "south": {
                  "uv": [
                    73.0,
                    68.0
                  ],
                  "uv_size": [
                    10.0,
                    1.0
                  ]
                },
                "west": {
                  "uv": [
                    64.0,
                    68.0
                  ],
                  "uv_size": [
                    9.0,
                    1.0
                  ]
                },
                "up": {
                  "uv": [
                    83.0,
                    68.0
                  ],
                  "uv_size": [
                    -10.0,
                    -9.0
                  ]
                },
                "down": {
                  "uv": [
                    93.0,
                    68.0
                  ],
                  "uv_size": [
                    -10.0,
                    -9.0
                  ]
                }
              }
            }
          ]
        },
        {
          "name": "wing2",
          "pivot": [
            1.1,
            36.3,
            -1.1
          ],
          "parent": "top_1",
          "rotation": [
            179.99997,
            -44.96003,
            177.39001
          ],
          "cubes": [
            {
              "origin": [
                -8.9,
                35.3,
                -5.6
              ],
              "size": [
                10.0,
                1.0,
                9.0
              ],
              "uv": {
                "north": {
                  "uv": [
                    28.0,
                    78.0
                  ],
                  "uv_size": [
                    10.0,
                    1.0
                  ]
                },
                "east": {
                  "uv": [
                    19.0,
                    78.0
                  ],
                  "uv_size": [
                    9.0,
                    1.0
                  ]
                },
                "south": {
                  "uv": [
                    9.0,
                    78.0
                  ],
                  "uv_size": [
                    10.0,
                    1.0
                  ]
                },
                "west": {
                  "uv": [
                    0.0,
                    78.0
                  ],
                  "uv_size": [
                    9.0,
                    1.0
                  ]
                },
                "up": {
                  "uv": [
                    19.0,
                    78.0
                  ],
                  "uv_size": [
                    -10.0,
                    -9.0
                  ]
                },
                "down": {
                  "uv": [
                    29.0,
                    78.0
                  ],
                  "uv_size": [
                    -10.0,
                    -9.0
                  ]
                }
              }
            }
          ]
        },
        {
          "name": "wing3",
          "pivot": [
            -0.1,
            36.3,
            1.3
          ],
          "parent": "top_1",
          "rotation": [
            180.0,
            45.0,
            180.0
          ],
          "cubes": [
            {
              "origin": [
                -10.1,
                35.3,
                -3.2
              ],
              "size": [
                10.0,
                1.0,
                9.0
              ],
              "uv": {
                "north": {
                  "uv": [
                    66.0,
                    78.0
                  ],
                  "uv_size": [
                    10.0,
                    1.0
                  ]
                },
                "east": {
                  "uv": [
                    57.0,
                    78.0
                  ],
                  "uv_size": [
                    9.0,
                    1.0
                  ]
                },
                "south": {
                  "uv": [
                    47.0,
                    78.0
                  ],
                  "uv_size": [
                    10.0,
                    1.0
                  ]
                },
                "west": {
                  "uv": [
                    38.0,
                    78.0
                  ],
                  "uv_size": [
                    9.0,
                    1.0
                  ]
                },
                "up": {
                  "uv": [
                    57.0,
                    78.0
                  ],
                  "uv_size": [
                    -10.0,
                    -9.0
                  ]
                },
                "down": {
                  "uv": [
                    67.0,
                    78.0
                  ],
                  "uv_size": [
                    -10.0,
                    -9.0
                  ]
                }
              }
            }
          ]
        },
        {
          "name": "wing1_1",
          "pivot": [
            -11.2,
            36.3,
            -1.1
          ],
          "parent": "wing1",
          "rotation": [
            0.0,
            0.0,
            -23.0
          ],
          "cubes": [
            {
              "origin": [
                -21.2,
                35.3,
                -5.6
              ],
              "size": [
                10.0,
                1.0,
                9.0
              ],
              "uv": {
                "north": {
                  "uv": [
                    104.0,
                    78.0
                  ],
                  "uv_size": [
                    10.0,
                    1.0
                  ]
                },
                "east": {
                  "uv": [
                    95.0,
                    78.0
                  ],
                  "uv_size": [
                    9.0,
                    1.0
                  ]
                },
                "south": {
                  "uv": [
                    85.0,
                    78.0
                  ],
                  "uv_size": [
                    10.0,
                    1.0
                  ]
                },
                "west": {
                  "uv": [
                    76.0,
                    78.0
                  ],
                  "uv_size": [
                    9.0,
                    1.0
                  ]
                },
                "up": {
                  "uv": [
                    95.0,
                    78.0
                  ],
                  "uv_size": [
                    -10.0,
                    -9.0
                  ]
                },
                "down": {
                  "uv": [
                    105.0,
                    78.0
                  ],
                  "uv_size": [
                    -10.0,
                    -9.0
                  ]
                }
              }
            }
          ]
        },
        {
          "name": "wing2_2",
          "pivot": [
            -8.9,
            36.3,
            -1.1
          ],
          "parent": "wing2",
          "rotation": [
            0.0,
            0.0,
            -23.0
          ],
          "cubes": [
            {
              "origin": [
                -18.9,
                35.3,
                -5.6
              ],
              "size": [
                10.0,
                1.0,
                9.0
              ],
              "uv": {
                "north": {
                  "uv": [
                    28.0,
                    88.0
                  ],
                  "uv_size": [
                    10.0,
                    1.0
                  ]
                },
                "east": {
                  "uv": [
                    19.0,
                    88.0
                  ],
                  "uv_size": [
                    9.0,
                    1.0
                  ]
                },
                "south": {
                  "uv": [
                    9.0,
                    88.0
                  ],
                  "uv_size": [
                    10.0,
                    1.0
                  ]
                },
                "west": {
                  "uv": [
                    0.0,
                    88.0
                  ],
                  "uv_size": [
                    9.0,
                    1.0
                  ]
                },
                "up": {
                  "uv": [
                    19.0,
                    88.0
                  ],
                  "uv_size": [
                    -10.0,
                    -9.0
                  ]
                },
                "down": {
                  "uv": [
                    29.0,
                    88.0
                  ],
                  "uv_size": [
                    -10.0,
                    -9.0
                  ]
                }
              }
            }
          ]
        },
        {
          "name": "wing3_3",
          "pivot": [
            -10.1,
            36.3,
            1.3
          ],
          "parent": "wing3",
          "rotation": [
            0.0,
            0.0,
            -23.0
          ],
          "cubes": [
            {
              "origin": [
                -20.1,
                35.3,
                -3.2
              ],
              "size": [
                10.0,
                1.0,
                9.0
              ],
              "uv": {
                "north": {
                  "uv": [
                    66.0,
                    88.0
                  ],
                  "uv_size": [
                    10.0,
                    1.0
                  ]
                },
                "east": {
                  "uv": [
                    57.0,
                    88.0
                  ],
                  "uv_size": [
                    9.0,
                    1.0
                  ]
                },
                "south": {
                  "uv": [
                    47.0,
                    88.0
                  ],
                  "uv_size": [
                    10.0,
                    1.0
                  ]
                },
                "west": {
                  "uv": [
                    38.0,
                    88.0
                  ],
                  "uv_size": [
                    9.0,
                    1.0
                  ]
                },
                "up": {
                  "uv": [
                    57.0,
                    88.0
                  ],
                  "uv_size": [
                    -10.0,
                    -9.0
                  ]
                },
                "down": {
                  "uv": [
                    67.0,
                    88.0
                  ],
                  "uv_size": [
                    -10.0,
                    -9.0
                  ]
                }
              }
            }
          ]
        }
      ]
    }
  ]
}